<?xml version = '1.0' encoding = 'UTF-8'?>
<FKIndexAssociation class="oracle.dbtools.crest.model.design.relational.FKIndexAssociation" directorySegmentName="seg_0" id="6166904B-0741-B081-F50E-BB46171D6358" name="Usuario_equipo_Equipo_FK">
<createdBy>Admin</createdBy>
<createdTime>2022-10-13 23:11:15 UTC</createdTime>
<generatorID>Generado por el Usuario</generatorID>
<ownerDesignName>ModeloDatos5</ownerDesignName>
<containerWithKeyObject>272981E4-B397-D064-7E7C-8213F428146E</containerWithKeyObject>
<deleteRule>NO ACTION</deleteRule>
<localFKIndex>6C3D2A86-8BCA-B7E6-3792-D7939D168FAD</localFKIndex>
<keyObject>6A66E432-1620-540B-BF09-D7FA5F52D36A</keyObject>
<mandatory>true</mandatory>
<transferable>true</transferable>
<columnDependencyConstraintGenerateInDDL>true</columnDependencyConstraintGenerateInDDL>
</FKIndexAssociation>